Metadata-Version: 2.1
Name: mlfc-distributions
Version: 1.3
Summary: Gaussian distributions
Home-page: https://udacity.com
Author: RK
Author-email: rom@mailinator.com
License: UNKNOWN
Platform: UNKNOWN
License-File: license.txt
